prival/__init__.py
prival/config.yaml
prival/core.py
prival/report.py
prival/scoring.py
prival/detectors/ambiguity.py
prival/detectors/clarity.py
prival/detectors/context_completeness.py
prival/detectors/diversity.py
prival/detectors/ethic_compliance.py
prival/detectors/feasibility.py
prival/detectors/grammar_spelling.py
prival/detectors/injection_risk.py
prival/detectors/length_appropriateness.py
prival/detectors/relevance.py
prival/detectors/step_guidance.py
prival/detectors/structural_cleanness.py
prival/detectors/verbosity.py
prival/utils/nlp_helpers.py
prival-0.1.9.dist-info/METADATA
prival-0.1.9.dist-info/WHEEL
prival-0.1.9.dist-info/top_level.txt
prival-0.1.9.dist-info/RECORD
