Metadata-Version: 2.4
Name: prival
Version: 0.1.9
Summary: Prompt Input Validation toolkit
Home-page: https://huggingface.co/EugeneXiang/prival
Author: Peng Xiang
Author-email: eugene.p.xiang@gmail.com
License: MIT
Classifier: Programming Language :: Python :: 3
Classifier: License :: OSI Approved :: MIT License
Classifier: Operating System :: OS Independent
Requires-Python: >=3.7
Requires-Dist: pyyaml
Requires-Dist: language-tool-python
Requires-Dist: sentence-transformers
Provides-Extra: full
Requires-Dist: spacy; extra == "full"
Dynamic: author
Dynamic: author-email
Dynamic: classifier
Dynamic: description
Dynamic: description-content-type
Dynamic: home-page
Dynamic: license
Dynamic: provides-extra
Dynamic: requires-dist
Dynamic: requires-python
Dynamic: summary
